budtiktok/__init__.py
budtiktok/__init__.pyi
budtiktok/budtiktok.abi3.so
budtiktok-0.1.0.dist-info/METADATA
budtiktok-0.1.0.dist-info/WHEEL
budtiktok-0.1.0.dist-info/RECORD
