Metadata-Version: 2.4
Name: budtiktok
Version: 0.1.0
Classifier: Development Status :: 4 - Beta
Classifier: Intended Audience :: Developers
Classifier: Intended Audience :: Science/Research
Classifier: License :: OSI Approved :: Apache Software License
Classifier: Operating System :: OS Independent
Classifier: Programming Language :: Python :: 3
Classifier: Programming Language :: Python :: 3.8
Classifier: Programming Language :: Python :: 3.9
Classifier: Programming Language :: Python :: 3.10
Classifier: Programming Language :: Python :: 3.11
Classifier: Programming Language :: Python :: 3.12
Classifier: Programming Language :: Rust
Classifier: Topic :: Scientific/Engineering :: Artificial Intelligence
Classifier: Topic :: Text Processing
Requires-Dist: numpy>=1.20.0
Requires-Dist: torch>=1.9.0 ; extra == 'all'
Requires-Dist: torch>=1.9.0 ; extra == 'torch'
Provides-Extra: all
Provides-Extra: torch
Summary: Ultra-fast HuggingFace-compatible tokenizer with SIMD and multi-core support
Keywords: tokenizer,nlp,transformers,bert,gpt,simd,rust
Author-email: LatentBud Team <team@latentbud.com>
License: Apache-2.0
Requires-Python: >=3.8
Project-URL: Documentation, https://github.com/BudEcosystem/budtiktok#readme
Project-URL: Homepage, https://github.com/BudEcosystem/budtiktok
Project-URL: Issues, https://github.com/BudEcosystem/budtiktok/issues
Project-URL: Repository, https://github.com/BudEcosystem/budtiktok
